sentence_tk_checker/__init__.py
sentence_tk_checker/tokenizer_checker.py
sentence_tk_checker-0.0.2.dist-info/LICENSE.txt
sentence_tk_checker-0.0.2.dist-info/METADATA
sentence_tk_checker-0.0.2.dist-info/WHEEL
sentence_tk_checker-0.0.2.dist-info/top_level.txt
sentence_tk_checker-0.0.2.dist-info/RECORD
