Metadata-Version: 2.1
Name: sentence-tk-checker
Version: 0.0.2
Summary: Checks output of an English sentence tokenizer and modifies the output according to default or user-defined rules.
Home-page: https://github.com/Rairye/sentence-tk-checker
Download-URL: https://github.com/Rairye/sentence-tk-checker/archive/refs/tags/v0.0.2.tar.gz
Author: Rairye
License: apache-2.0
Keywords: english,sentence,split,tokenization
Classifier: Development Status :: 3 - Alpha
Classifier: Intended Audience :: End Users/Desktop
Classifier: Intended Audience :: Developers
Classifier: License :: OSI Approved :: Apache Software License
Classifier: Programming Language :: Python :: 3
Classifier: Programming Language :: Python :: 3.1
Classifier: Programming Language :: Python :: 3.2
Classifier: Programming Language :: Python :: 3.3
Classifier: Programming Language :: Python :: 3.4
Classifier: Programming Language :: Python :: 3.5
Classifier: Programming Language :: Python :: 3.6
Classifier: Programming Language :: Python :: 3.7
License-File: LICENSE.txt
